MapLines/__init__.py
MapLines/common/__init__.py
MapLines/common/constants.py
MapLines/tools/__init__.py
MapLines/tools/line_fit.py
MapLines/tools/mcmc.py
MapLines/tools/models.py
MapLines/tools/plot_tools.py
MapLines/tools/priors.py
MapLines/tools/tools.py
mapline-2.0.0.data/scripts/run_mapline
mapline-2.0.0.dist-info/METADATA
mapline-2.0.0.dist-info/WHEEL
mapline-2.0.0.dist-info/top_level.txt
mapline-2.0.0.dist-info/RECORD
