Metadata-Version: 2.4
Name: MapLine
Version: 2.0.0
Summary: A Python implementation of the 3D emission line fitting code
Home-page: https://github.com/hjibarram/Map_line
Download-URL: https://github.com/hjibarram/Map_line/archive/refs/tags/v2.0.0.tar.gz
Author: hjibarram
Author-email: hjibarram@gmail.com
License: MIT
Keywords: galaxies
Classifier: Development Status :: 5 - Production/Stable
Classifier: License :: OSI Approved :: MIT License
Classifier: Programming Language :: Python :: 3.8
Classifier: Topic :: Scientific/Engineering :: Astronomy
Requires-Dist: astropy
Requires-Dist: matplotlib
Requires-Dist: numpy
Requires-Dist: scipy
Requires-Dist: cloup
Requires-Dist: click
Requires-Dist: emcee
Requires-Dist: tqdm
Requires-Dist: corner
Requires-Dist: numpy-stl
Dynamic: author
Dynamic: author-email
Dynamic: classifier
Dynamic: description
Dynamic: description-content-type
Dynamic: download-url
Dynamic: home-page
Dynamic: keywords
Dynamic: license
Dynamic: requires-dist
Dynamic: summary
